{
  "ComponentIndexes": {},
  "ControlUniqueGuids": {},
  "ControlUniqueIds": {
    "App": 1,
    "Circle1": 33,
    "CNIC InputField_2": 60,
    "CNIC InputField_3": 64,
    "CNICInputField": 53,
    "ConfirmPassword": 62,
    "Dropdown2": 19,
    "Email InputField": 47,
    "FirstNameInputField": 45,
    "Gallery1": 10,
    "galleryTemplate1": 11,
    "galleryTemplate2": 32,
    "Home Screen": 3,
    "IBA": 29,
    "Icon1": 61,
    "Icon1_1": 65,
    "iconNext1": 37,
    "iconPrev1": 36,
    "Image1": 4,
    "Image2": 5,
    "Image79": 13,
    "Image79_1": 39,
    "Image812": 15,
    "Image812_1": 41,
    "Image814": 14,
    "Image814_1": 40,
    "Label1_1": 49,
    "Label1_2": 54,
    "Label2": 7,
    "Label3": 6,
    "Label813": 16,
    "Label813_1": 42,
    "Label816": 18,
    "LabelSkip1": 34,
    "LastName InputField": 46,
    "Login btn": 23,
    "Login Region": 27,
    "Login Screen": 12,
    "Login TextField": 20,
    "Logo Region": 26,
    "Logo Region_1": 67,
    "NationalityLabel": 50,
    "Oboarding Screen": 28,
    "Or Text": 24,
    "Password": 58,
    "Password Label": 22,
    "Password TextField": 21,
    "PhoneNumber InputField_1": 48,
    "ProgramsDropDown": 56,
    "ProgramsDropDown_1": 57,
    "ProgramsInterestedIn": 55,
    "Radio1": 52,
    "Rectangle1": 8,
    "Rectangle67": 17,
    "Rectangle67_1": 43,
    "Register Label": 44,
    "Register Region": 68,
    "Register Screen": 38,
    "Registerbtn": 25,
    "RegisterBtn": 66,
    "Star1": 51,
    "Star1_1": 59,
    "Star1_2": 63,
    "StartWithApplication": 9,
    "TutorialImage1": 30,
    "TutorialNavigator1": 31,
    "TutorialText1": 35
  },
  "FunctionParamsInvariantScripts": {},
  "FunctionParamsInvariantScriptsOnInstances": {},
  "HeaderLastSavedDateTimeUTC": "10/19/2022 11:08:16",
  "IsLegacyComponentAllowGlobalScopeCase": false,
  "LocalConnectionIDReferences": {
    "7580dfef-b203-40b2-8d5e-98aa9e654967": "\"/providers/microsoft.powerapps/apis/shared_sharepointonline/connections/fd61e08e61b4462c845da42bde057db0\""
  },
  "LocalDatabaseReferencesAsEmpty": false,
  "LocalResourceFileNames": {
    "IBABackground": "0001.jpg",
    "Institute_of_Business_Administration,_Karachi_(logo)": "0002.png",
    "png-transparent-institute-of-business-administration-karachi-sukkur-iba-university-business-school-master-of-business-administration-management-school": "0003.png",
    "White Background": "0004.png"
  },
  "LocalResourceRootPaths": {
    "IBABackground": "https://docserverpwaprodneu.blob.core.windows.net/48e4c926-1525-41a0-bdfd-571d49b7534b-1/resource/Assets0Images00001.jpg?sv=2017-04-17&sr=b&sig=JDVqGfNkQd1GdrTQi%2Bo%2FZx07E5%2BP432n8IbxI0p3go4%3D&spr=https&se=2022-10-20T09%3A18%3A37Z&sp=r",
    "Institute_of_Business_Administration,_Karachi_(logo)": "https://docserverpwaprodneu.blob.core.windows.net/48e4c926-1525-41a0-bdfd-571d49b7534b-1/resource/Assets0Images00002.png?sv=2017-04-17&sr=b&sig=Ne%2FSA5Lxtlom6K677sZjvs%2Bp%2FIvzLEGbAXH4HiAvSCQ%3D&spr=https&se=2022-10-20T09%3A18%3A37Z&sp=r",
    "png-transparent-institute-of-business-administration-karachi-sukkur-iba-university-business-school-master-of-business-administration-management-school": "https://docserverpwaprodneu.blob.core.windows.net/48e4c926-1525-41a0-bdfd-571d49b7534b-1/resource/Assets0Images00003.png?sv=2017-04-17&sr=b&sig=SPqF9N0ZAhxsYpxZoPh63VE9eEv%2FF46IDwy%2FVCGDihY%3D&spr=https&se=2022-10-20T09%3A18%3A37Z&sp=r",
    "White Background": "https://docserverpwaprodneu.blob.core.windows.net/48e4c926-1525-41a0-bdfd-571d49b7534b-1/resource/Assets0Images00004.png?sv=2017-04-17&sr=b&sig=hdvL52Pijeks19ZtVeOdu0jYYxNuqs6zAF9SimX13KI%3D&spr=https&se=2022-10-20T09%3A18%3A37Z&sp=r"
  },
  "OldLogoFileName": "logo.jpg",
  "OrderComponentMetadata": {},
  "OrderComponentTemplate": {},
  "OrderDataSource": {
    "ComboBoxSample": 4,
    "CustomGallerySample": 0,
    "DropDownSample": 1,
    "RadioSample": 2,
    "StatusColors": 5,
    "Users": 3
  },
  "OrderGroupControls": {
    "Login Region": {
      "Dropdown2": 7,
      "Label816": 1,
      "Login btn": 3,
      "Login TextField": 8,
      "Or Text": 5,
      "Password Label": 2,
      "Password TextField": 6,
      "Rectangle67": 0,
      "Registerbtn": 4
    },
    "Logo Region": {
      "Image812": 2,
      "Image814": 0,
      "Label813": 1
    },
    "Logo Region_1": {
      "Image812_1": 2,
      "Image814_1": 0,
      "Label813_1": 1
    },
    "Register Region": {
      "CNIC InputField_2": 14,
      "CNIC InputField_3": 15,
      "CNICInputField": 9,
      "ConfirmPassword": 17,
      "Email InputField": 4,
      "FirstNameInputField": 3,
      "Icon1": 18,
      "Icon1_1": 19,
      "Label1_1": 10,
      "Label1_2": 23,
      "LastName InputField": 5,
      "NationalityLabel": 8,
      "Password": 16,
      "PhoneNumber InputField_1": 6,
      "ProgramsDropDown": 12,
      "ProgramsDropDown_1": 22,
      "ProgramsInterestedIn": 13,
      "Radio1": 7,
      "Rectangle67_1": 0,
      "Register Label": 1,
      "RegisterBtn": 2,
      "Star1": 11,
      "Star1_1": 20,
      "Star1_2": 21
    }
  },
  "OrderPcfTemplate": {},
  "OrderTemplate": {},
  "OrderXMLTemplate": {
    "button": 6,
    "circle": 7,
    "dropdown": 4,
    "gallery": 3,
    "icon": 8,
    "image": 0,
    "label": 1,
    "radio": 10,
    "rectangle": 2,
    "star": 9,
    "text": 5
  },
  "PublishOrderIndices": {
    "App": 0,
    "Circle1": 57,
    "CNIC InputField_2": 38,
    "CNIC InputField_3": 42,
    "CNICInputField": 31,
    "ConfirmPassword": 40,
    "Dropdown2": 8,
    "Email InputField": 25,
    "FirstNameInputField": 23,
    "Gallery1": 51,
    "galleryTemplate1": 52,
    "galleryTemplate2": 56,
    "Home Screen": 2,
    "IBA": 53,
    "Icon1": 39,
    "Icon1_1": 43,
    "iconNext1": 61,
    "iconPrev1": 60,
    "Image1": 45,
    "Image2": 46,
    "Image79": 0,
    "Image79_1": 15,
    "Image812": 3,
    "Image812_1": 18,
    "Image814": 1,
    "Image814_1": 16,
    "Label1_1": 27,
    "Label1_2": 32,
    "Label2": 48,
    "Label3": 47,
    "Label813": 4,
    "Label813_1": 19,
    "Label816": 7,
    "LabelSkip1": 58,
    "LastName InputField": 24,
    "Login btn": 12,
    "Login Region": 6,
    "Login Screen": 11,
    "Login TextField": 9,
    "Logo Region": 2,
    "Logo Region_1": 17,
    "NationalityLabel": 28,
    "Oboarding Screen": 27,
    "Or Text": 13,
    "Password": 36,
    "Password Label": 11,
    "Password TextField": 10,
    "PhoneNumber InputField_1": 26,
    "ProgramsDropDown": 34,
    "ProgramsDropDown_1": 35,
    "ProgramsInterestedIn": 33,
    "Radio1": 30,
    "Rectangle1": 49,
    "Rectangle67": 5,
    "Rectangle67_1": 20,
    "Register Label": 22,
    "Register Region": 21,
    "Register Screen": 37,
    "Registerbtn": 14,
    "RegisterBtn": 44,
    "Star1": 29,
    "Star1_1": 37,
    "Star1_2": 41,
    "StartWithApplication": 50,
    "TutorialImage1": 54,
    "TutorialNavigator1": 55,
    "TutorialText1": 59
  },
  "ResourcesJsonIndices": {
    "Image-IBABackground": 1,
    "Image-Institute_of_Business_Administration,_Karachi_(logo)": 2,
    "Image-png-transparent-institute-of-business-administration-karachi-sukkur-iba-university-business-school-master-of-business-administration-management-school": 3,
    "Image-SampleImage": 0,
    "Image-White Background": 4
  },
  "RuleScreenIdWithoutScreen": {},
  "TemplateVersions": {},
  "VolatileProperties": {
    "AnalysisLoadTime": 0.5021712,
    "ControlCount": {
      "button": 3,
      "circle": 1,
      "dropdown": 3,
      "gallery": 2,
      "galleryTemplate": 2,
      "group": 4,
      "icon": 4,
      "image": 10,
      "label": 17,
      "radio": 1,
      "rectangle": 3,
      "screen": 4,
      "star": 3,
      "text": 9
    },
    "DeserializationLoadTime": 0.8541815,
    "ErrorCount": 4
  },
  "WasLocalDatabaseReferencesEmpty": true
}